django_huey-stubs/__init__.pyi
django_huey-stubs/config.pyi
django_huey-stubs/exceptions.pyi
django_huey-stubs/management/__init__.pyi
django_huey-stubs/management/commands/__init__.pyi
django_huey-stubs/management/commands/djangohuey.pyi
django_huey-stubs/models.pyi
django_huey-stubs/utils.pyi
django_huey_stubs-0.0.3.dist-info/LICENSE
django_huey_stubs-0.0.3.dist-info/WHEEL
django_huey_stubs-0.0.3.dist-info/METADATA
django_huey_stubs-0.0.3.dist-info/RECORD
